anypush/__init__.py
anypush/envs/__init__.py
anypush/envs/anypush_env.py
anypush/envs/anypush_image_env.py
anypush/envs/anypush_keypoints_env.py
anypush/envs/objects/__init__.py
anypush/envs/objects/alphabet/anypush_T.py
anypush/envs/objects/anypush_number.py
anypush/envs/objects/anypush_shape.py
anypush/envs/pymunk_keypoint_manager.py
anypush/envs/pymunk_override.py
anypush-3.9.1.dist-info/LICENSE
anypush-3.9.1.dist-info/METADATA
anypush-3.9.1.dist-info/WHEEL
anypush-3.9.1.dist-info/RECORD
